stcchecker/__init__.py
stcchecker/api.py
stcchecker-0.1.0.dist-info/licenses/LICENSE
stcchecker-0.1.0.dist-info/METADATA
stcchecker-0.1.0.dist-info/WHEEL
stcchecker-0.1.0.dist-info/top_level.txt
stcchecker-0.1.0.dist-info/RECORD
