Metadata-Version: 2.4
Name: stcchecker
Version: 0.1.0
Summary: A wrapper for STC API
Home-page: https://pypi.org/project/stcchecker/
Author: HARSHVARDHAN (@technopile)
Author-email: youremail@example.com
License: Custom License - HARSHVARDHAN (@technopile)
License-File: LICENSE
Requires-Dist: requests
Dynamic: author
Dynamic: author-email
Dynamic: description
Dynamic: description-content-type
Dynamic: home-page
Dynamic: license
Dynamic: license-file
Dynamic: requires-dist
Dynamic: summary
